flomp/__init__.py
flomp/flomp.py
flomp/flompDataHandling.py
flomp/flompMath.py
flomp/flompPlot.py
flomp-0.1.4.dist-info/METADATA
flomp-0.1.4.dist-info/WHEEL
flomp-0.1.4.dist-info/top_level.txt
flomp-0.1.4.dist-info/RECORD
