Metadata-Version: 2.4
Name: flomp
Version: 0.1.4
Summary: collection of functions used throughout all projects of curiousMonkey, making them importable as package
Requires-Python: >=3.12
